odoo/addons/web_widget_dropdown_dynamic_example/__init__.py
odoo/addons/web_widget_dropdown_dynamic_example/__manifest__.py
odoo/addons/web_widget_dropdown_dynamic_example/i18n/web_widget_dropdown_dynamic_example.pot
odoo/addons/web_widget_dropdown_dynamic_example/models/__init__.py
odoo/addons/web_widget_dropdown_dynamic_example/models/web_widget_dropdown_dynamic_example.py
odoo/addons/web_widget_dropdown_dynamic_example/static/description/icon.png
odoo/addons/web_widget_dropdown_dynamic_example/views/web_widget_dropdown_dynamic_example.xml
odoo11_addon_web_widget_dropdown_dynamic_example-11.0.1.0.1.dist-info/METADATA
odoo11_addon_web_widget_dropdown_dynamic_example-11.0.1.0.1.dist-info/WHEEL
odoo11_addon_web_widget_dropdown_dynamic_example-11.0.1.0.1.dist-info/top_level.txt
odoo11_addon_web_widget_dropdown_dynamic_example-11.0.1.0.1.dist-info/RECORD
